jast/__init__.py
jast/_jast.py
jast/_parse.py
jast/_unparse.py
jast/_visitors.py
jast/_visitors.pyi
jast/_parser/JavaLexer.py
jast/_parser/JavaParser.py
jast/_parser/JavaParserListener.py
jast/_parser/JavaParserVisitor.py
jast/_parser/__init__.py
jast/_parser/_convert.py
java_ast-1.0.0.dist-info/LICENSE
java_ast-1.0.0.dist-info/METADATA
java_ast-1.0.0.dist-info/WHEEL
java_ast-1.0.0.dist-info/top_level.txt
java_ast-1.0.0.dist-info/RECORD
