Metadata-Version: 2.2
Name: java-ast
Version: 1.0.0
Summary: jAST: Analyzing and Modifying Java ASTs with Python
Author-email: Marius Smytzek <marius.smytzek@cispa.de>, Martin Eberlein <martin.eberlein@hu-berlin.de>
Project-URL: Homepage, https://github.com/smythi93/jast
Project-URL: Bug Tracker, https://github.com/smythi93/jast/issues
Classifier: Intended Audience :: Science/Research
Classifier: Programming Language :: Python :: 3.10
Classifier: License :: OSI Approved :: MIT License
Classifier: Topic :: Scientific/Engineering
Classifier: Topic :: Software Development :: Testing
Classifier: Topic :: Software Development :: Libraries
Requires-Python: >=3.10
License-File: LICENSE
Requires-Dist: antlr4-python3-runtime>=4.13.2
Provides-Extra: test
Requires-Dist: pytest>=8.3.4; extra == "test"
Requires-Dist: pytest-cov>=6.0.0; extra == "test"
Requires-Dist: pytest-html>=4.1.1; extra == "test"
Requires-Dist: parameterized>=0.9.0; extra == "test"
